{
"dcterms:identifier":"sugawara_B-031",
"mods:physicalLocation":"KC-39",
"sugawara:folder":"KC",
"schema:category":"iqrar style",
"dcterms:subject":[],
"dcterms:description":"不動産売却",
"sugawara:physicaldata":"ゆnum_old　 印花　",
"sugawara:phystype":"",
"sugawara:taxStamp":"YH01A_1913",
"sugawara:document":"document",
"crossasia:dateOriginal":"1335-12-20",
"crossasia:yearOriginal":"1335",
"sugawara:hijuriYear":"",
"sugawara:hijuriMonth":"Dhu al-hijja",
"sugawara:dow":"",
"crossasia:wholedate":"1917-10-07",
"dc:date":["1917"],
"crossasia:adminlevel1":"Kashgar city",
"crossasia:adminlevel2":"Quruq Turk mehellisi",
"crossasia:placeType2":"Neighbourhood/Vicinity",
"crossasia:placeType3":"",
"sugawara:place":[],
"dc:place":["Kashgar, Quruq Turk mahallasi"],
"sugawara:personRoleA":[],
"sugawara:RoleA":"",
"schema:personRoleB":[],
"sugawara:RoleB":"",
"sugawara:seal":[],
"dcterms:language":"chg",
"crossasia:language":"Chagatai",
"schema:abstract":"",
"schema:citation":"",
"schema:grant":"<KAKENHI> 研究費 (Japan Society for the Promotion of Science)",
"dcterms:extent":"1 folio, recto-verso",
"pages":[{"name":"B031a.jpg","alben":"B031","id":"4","position":"4"},{"name":"B031b.jpg","alben":"B031","id":"5","position":"5"},{"name":"O_B031.jpg","alben":"B031","id":"6","position":"6"}]
}
