{
"dcterms:identifier":"sugawara_D-107",
"mods:physicalLocation":"KD-198",
"sugawara:folder":"KD",
"schema:category":"iqrar style",
"dcterms:subject":[],
"dcterms:description":["madyun","債務文書","現金"],
"sugawara:physicaldata":"ゆ　印花",
"sugawara:phystype":"",
"sugawara:taxStamp":"YH08_1951",
"sugawara:document":"document",
"crossasia:dateOriginal":"1370-12-02",
"crossasia:yearOriginal":"1370",
"sugawara:hijuriYear":"",
"sugawara:hijuriMonth":"Dhu al-hijja",
"sugawara:dow":"",
"crossasia:wholedate":"1951-09-04",
"dc:date":["1951"],
"crossasia:adminlevel1":"Kashgar region",
"crossasia:adminlevel2":"Tazghun",
"crossasia:placeType2":"",
"crossasia:placeType3":"",
"sugawara:place":"Uzun Saqal kent",
"dc:place":["Kashgar, Tazghun, Uzun Saqal kent"],
"sugawara:personRoleA":"Hashim Akhun b. Turdi Akhun",
"sugawara:RoleA":"",
"schema:personRoleB":"Tala Khan b. Dhulal Husayn Akhund",
"sugawara:RoleB":"",
"sugawara:seal":[],
"dcterms:language":"chg",
"crossasia:language":"Chagatai",
"schema:abstract":"",
"schema:citation":"",
"schema:grant":"<KAKENHI> 研究費 (Japan Society for the Promotion of Science)",
"dcterms:extent":"1 folio, recto",
"pages":[{"name":"D107.jpg","alben":"D107","id":"4","position":"4"},{"name":"O_D107.jpg","alben":"D107","id":"5","position":"5"}]
}
