{
"dcterms:identifier":"sugawara_D-189",
"mods:physicalLocation":"KD-N",
"sugawara:folder":"KD",
"schema:category":"Chinese form",
"dcterms:subject":[],
"dcterms:description":["Chinese form","完納額糧執照"],
"sugawara:physicaldata":"他",
"sugawara:phystype":"",
"sugawara:taxStamp":[],
"sugawara:document":"document",
"crossasia:dateOriginal":"",
"crossasia:yearOriginal":"",
"sugawara:hijuriYear":"",
"sugawara:hijuriMonth":"",
"sugawara:dow":"",
"crossasia:wholedate":"date unclear",
"dc:date":["date unclear"],
"crossasia:adminlevel1":"Khotan region",
"crossasia:adminlevel2":"",
"crossasia:placeType2":"",
"crossasia:placeType3":"",
"sugawara:place":[],
"dc:place":["Khotan"],
"sugawara:personRoleA":[],
"sugawara:RoleA":"",
"schema:personRoleB":[],
"sugawara:RoleB":"",
"sugawara:seal":[],
"dcterms:language":["chg","chi"],
"crossasia:language":["Chagatai","Chinese"],
"schema:abstract":"",
"schema:citation":"",
"schema:grant":"<KAKENHI> 研究費 (Japan Society for the Promotion of Science)",
"dcterms:extent":"1 folio, recto",
"pages":[{"name":"D189.jpg","alben":"D189","id":"4","position":"4"}]
}
